substrateinterface_subsquid/__init__.py
substrateinterface_subsquid/extensions.py
substrate_interface_subsquid-0.1.dist-info/LICENSE
substrate_interface_subsquid-0.1.dist-info/METADATA
substrate_interface_subsquid-0.1.dist-info/WHEEL
substrate_interface_subsquid-0.1.dist-info/top_level.txt
substrate_interface_subsquid-0.1.dist-info/RECORD
