Metadata-Version: 2.1
Name: substrate-interface-subsquid
Version: 0.1
Summary: py-substrate-interface extension to utilize Subsquid indexes
Home-page: https://github.com/polkascan/py-substrate-interface-extension-subsquid
Author: Stichting Polkascan (Polkascan Foundation)
Author-email: info@polkascan.org
License: UNKNOWN
Keywords: substrate-interface extension subsquid
Platform: UNKNOWN
Classifier: Development Status :: 3 - Alpha
Classifier: Intended Audience :: Developers
Classifier: License :: OSI Approved :: Apache Software License
Classifier: Programming Language :: Python :: 3
Classifier: Programming Language :: Python :: 3.7
Classifier: Programming Language :: Python :: 3.8
Classifier: Programming Language :: Python :: 3.9
Classifier: Programming Language :: Python :: 3.10
Classifier: Programming Language :: Python :: 3.11
Requires-Python: >=3.7, <4
Requires-Dist: substrate-interface (<2,>=1.7.1)
Requires-Dist: gql[aiohttp] (~=3.4.0)
Provides-Extra: test
Requires-Dist: coverage ; extra == 'test'
Requires-Dist: pytest ; extra == 'test'
